datasette_openai/__init__.py
datasette_openai-0.2.dist-info/LICENSE
datasette_openai-0.2.dist-info/METADATA
datasette_openai-0.2.dist-info/WHEEL
datasette_openai-0.2.dist-info/entry_points.txt
datasette_openai-0.2.dist-info/top_level.txt
datasette_openai-0.2.dist-info/RECORD
