Metadata-Version: 2.1
Name: datasette-openai
Version: 0.2
Summary: SQL functions for calling OpenAI APIs
Home-page: https://github.com/simonw/datasette-openai
Author: Simon Willison
License: Apache License, Version 2.0
Project-URL: Issues, https://github.com/simonw/datasette-openai/issues
Project-URL: CI, https://github.com/simonw/datasette-openai/actions
Project-URL: Changelog, https://github.com/simonw/datasette-openai/releases
Classifier: Framework :: Datasette
Classifier: License :: OSI Approved :: Apache Software License
Requires-Python: >=3.7
License-File: LICENSE
Requires-Dist: datasette
Requires-Dist: regex
Provides-Extra: test
Requires-Dist: pytest ; extra == 'test'
Requires-Dist: pytest-asyncio ; extra == 'test'
